fsqlfly/__init__.py
fsqlfly/app.py
fsqlfly/base_handle.py
fsqlfly/common.py
fsqlfly/db_helper.py
fsqlfly/db_models.py
fsqlfly/env.template
fsqlfly/main.py
fsqlfly/settings.py
fsqlfly/workflow.py
fsqlfly/airflow_plugins/__init__.py
fsqlfly/connection_manager/__init__.py
fsqlfly/contrib/__init__.py
fsqlfly/contrib/canal/__init__.py
fsqlfly/contrib/mail/__init__.py
fsqlfly/contrib/tests/__init__.py
fsqlfly/contrib/tests/test_mail.py
fsqlfly/handles/__init__.py
fsqlfly/handles/api_handler.py
fsqlfly/handles/crud_handler.py
fsqlfly/handles/file_handler.py
fsqlfly/handles/job_handler.py
fsqlfly/handles/manager_handler.py
fsqlfly/handles/terminal_handler.py
fsqlfly/helper/__init__.py
fsqlfly/job_manager/__init__.py
fsqlfly/job_manager/daemon.py
fsqlfly/static/asset-manifest.json
fsqlfly/static/favicon.png
fsqlfly/static/favicon2.png
fsqlfly/static/index.html
fsqlfly/static/layouts__BasicLayout.async.js
fsqlfly/static/layouts__BasicLayout.chunk.css
fsqlfly/static/p__job.async.js
fsqlfly/static/p__job__model.ts.async.js
fsqlfly/static/p__log.async.js
fsqlfly/static/p__login.async.js
fsqlfly/static/p__login.chunk.css
fsqlfly/static/p__login__model.ts.async.js
fsqlfly/static/p__resources.async.js
fsqlfly/static/p__resources.chunk.css
fsqlfly/static/p__resources__connection.async.js
fsqlfly/static/p__resources__connection__model.ts.async.js
fsqlfly/static/p__resources__connection__name__[id].async.js
fsqlfly/static/p__resources__connection__name__model.ts.async.js
fsqlfly/static/p__resources__connection__name__template__[nid].async.js
fsqlfly/static/p__resources__connection__name__template__model.ts.async.js
fsqlfly/static/p__resources__connection__name__template__version__[vid].async.js
fsqlfly/static/p__resources__connection__name__template__version__model.ts.async.js
fsqlfly/static/p__resources__connector.async.js
fsqlfly/static/p__resources__connector__model.ts.async.js
fsqlfly/static/p__resources__file.async.js
fsqlfly/static/p__resources__file__model.ts.async.js
fsqlfly-5.0.1.dist-info/METADATA
fsqlfly-5.0.1.dist-info/WHEEL
fsqlfly-5.0.1.dist-info/entry_points.txt
fsqlfly-5.0.1.dist-info/top_level.txt
fsqlfly-5.0.1.dist-info/RECORD
