Metadata-Version: 2.1
Name: fsqlfly
Version: 5.0.1
Summary: Flink SQL Job Management Website
Home-page: https://github.com/mrzhangboss/fsqlfly
Author: mrzhangboss
Author-email: 2529450174@qq.com
License: UNKNOWN
Platform: UNKNOWN
Classifier: Programming Language :: Python :: 3
Classifier: License :: OSI Approved :: MIT License
Classifier: Operating System :: OS Independent
Requires-Python: >=3.6.0
Requires-Dist: tornado (<=6.0.4)
Requires-Dist: terminado (<=0.8.3)
Requires-Dist: python-dotenv (<=0.12.0)
Requires-Dist: logzero (<=1.5.0)
Requires-Dist: PyYAML (<=5.3.1)
Requires-Dist: Jinja2 (<=2.11.1)
Requires-Dist: python-magic (<=0.4.15)
Requires-Dist: requests (<=2.23.0)
Requires-Dist: attrs (<=19.3.0)
Requires-Dist: sqlalchemy (<=1.3.15)
Requires-Dist: sqlalchemy-utils (<=0.36.3)
Provides-Extra: airflow
Requires-Dist: apache-airflow ; extra == 'airflow'
Provides-Extra: all
Requires-Dist: PyMySQL (<=0.9.3) ; extra == 'all'
Requires-Dist: psycopg2 (<=2.8.4) ; extra == 'all'
Requires-Dist: canal-python (<=0.4) ; extra == 'all'
Requires-Dist: kafka-python (<=1.4.7,>=1.3.4) ; extra == 'all'
Requires-Dist: protobuf (<=3.11.3) ; extra == 'all'
Requires-Dist: sqlalchemy (<=1.3.15) ; extra == 'all'
Requires-Dist: apache-airflow ; extra == 'all'
Requires-Dist: PyHive (<=0.6.2) ; extra == 'all'
Requires-Dist: thrift (<=0.13.0) ; extra == 'all'
Requires-Dist: sasl (<=0.2.1) ; extra == 'all'
Requires-Dist: thrift-sasl (<=0.4.2,>0.4.1) ; extra == 'all'
Requires-Dist: elasticsearch (<8.0.0,>=7.0.0) ; extra == 'all'
Requires-Dist: happybase (<=1.2.0) ; extra == 'all'
Provides-Extra: canal
Requires-Dist: canal-python (<=0.4) ; extra == 'canal'
Requires-Dist: kafka-python (<=1.4.7,>=1.3.4) ; extra == 'canal'
Requires-Dist: protobuf (<=3.11.3) ; extra == 'canal'
Requires-Dist: sqlalchemy (<=1.3.15) ; extra == 'canal'
Provides-Extra: es
Requires-Dist: elasticsearch (<8.0.0,>=7.0.0) ; extra == 'es'
Provides-Extra: hbase
Requires-Dist: happybase (<=1.2.0) ; extra == 'hbase'
Provides-Extra: hive
Requires-Dist: PyHive (<=0.6.2) ; extra == 'hive'
Requires-Dist: thrift (<=0.13.0) ; extra == 'hive'
Requires-Dist: sasl (<=0.2.1) ; extra == 'hive'
Requires-Dist: thrift-sasl (<=0.4.2,>0.4.1) ; extra == 'hive'
Provides-Extra: mysql
Requires-Dist: PyMySQL (<=0.9.3) ; extra == 'mysql'
Provides-Extra: postgresql
Requires-Dist: psycopg2 (<=2.8.4) ; extra == 'postgresql'
Provides-Extra: test
Requires-Dist: TorMySQL ; extra == 'test'
